traffic_weaver/__init__.py
traffic_weaver/_version.py
traffic_weaver/funfit.py
traffic_weaver/interval.py
traffic_weaver/match.py
traffic_weaver/process.py
traffic_weaver/rfa.py
traffic_weaver/sorted_array_utils.py
traffic_weaver/weaver.py
traffic_weaver/datasets/__init__.py
traffic_weaver/datasets/_ams_ix.py
traffic_weaver/datasets/_base.py
traffic_weaver/datasets/_datasets.py
traffic_weaver/datasets/_ix_br.py
traffic_weaver/datasets/_mix_it.py
traffic_weaver/datasets/_sandvine.py
traffic_weaver/datasets/data/__init__.py
traffic_weaver/datasets/data/sandvine/audio.csv
traffic_weaver/datasets/data/sandvine/cloud.csv
traffic_weaver/datasets/data/sandvine/file_sharing.csv
traffic_weaver/datasets/data/sandvine/fixed_social_media.csv
traffic_weaver/datasets/data/sandvine/gaming.csv
traffic_weaver/datasets/data/sandvine/marketplace.csv
traffic_weaver/datasets/data/sandvine/measurements.csv
traffic_weaver/datasets/data/sandvine/messaging.csv
traffic_weaver/datasets/data/sandvine/mobile_messaging.csv
traffic_weaver/datasets/data/sandvine/mobile_social_media.csv
traffic_weaver/datasets/data/sandvine/mobile_video.csv
traffic_weaver/datasets/data/sandvine/mobile_youtube.csv
traffic_weaver/datasets/data/sandvine/mobile_zoom.csv
traffic_weaver/datasets/data/sandvine/snapchat.csv
traffic_weaver/datasets/data/sandvine/social_networking.csv
traffic_weaver/datasets/data/sandvine/tiktok.csv
traffic_weaver/datasets/data/sandvine/video_streaming.csv
traffic_weaver/datasets/data/sandvine/vpn_and_security.csv
traffic_weaver/datasets/data/sandvine/web.csv
traffic_weaver/datasets/data_description/__init__.py
traffic_weaver/datasets/data_description/ams_ix.md
traffic_weaver/datasets/data_description/ix_br.md
traffic_weaver/datasets/data_description/mix_it.md
traffic_weaver/datasets/data_description/sandvine.md
traffic_weaver-1.5.4.dist-info/LICENSE
traffic_weaver-1.5.4.dist-info/METADATA
traffic_weaver-1.5.4.dist-info/WHEEL
traffic_weaver-1.5.4.dist-info/top_level.txt
traffic_weaver-1.5.4.dist-info/RECORD
