Metadata-Version: 2.1
Name: traffic-weaver
Version: 1.5.4
Summary: Semi-synthetic time-varrying traffic generator based on averaged time series
Author-email: "Piotr T. Lechowicz" <piotr.lechowicz@pwr.edu.pl>
Maintainer-email: "Piotr T. Lechowicz" <piotr.lechowicz@pwr.edu.pl>
License:                     GNU AFFERO GENERAL PUBLIC LICENSE
Project-URL: homepage, https://github.com/w4k2/traffic-weaver
Project-URL: documentation, https://w4k2.github.io/traffic-weaver/
Classifier: Development Status :: 3 - Alpha
Classifier: Programming Language :: Python :: 3.9
Requires-Python: >=3.9
License-File: LICENSE
Requires-Dist: scipy
Provides-Extra: dev
Requires-Dist: matplotlib; extra == "dev"
Requires-Dist: sphinx; extra == "dev"
Requires-Dist: sphinx-rtd-theme; extra == "dev"
Requires-Dist: sphinx-mdinclude; extra == "dev"
Requires-Dist: sphinxcontrib-bibtex; extra == "dev"
Requires-Dist: sphinx-markdown-tables; extra == "dev"
Requires-Dist: recommonmark; extra == "dev"
Requires-Dist: pandas; extra == "dev"
Requires-Dist: pytest; extra == "dev"
Requires-Dist: pytest-cov; extra == "dev"
Requires-Dist: pytest-mock; extra == "dev"
Requires-Dist: twine; extra == "dev"
Requires-Dist: pre-commit; extra == "dev"
Requires-Dist: coverage-badge; extra == "dev"
Requires-Dist: urllib3==1.26.6; extra == "dev"
